nrel_revx-0.5.4.dist-info/licenses/LICENSE
reVX/__init__.py
reVX/cli.py
reVX/version.py
reVX/config/__init__.py
reVX/config/least_cost_xmission.py
reVX/config/offshore.py
reVX/config/reeds.py
reVX/config/rpm.py
reVX/config/transmission_layer_creation.py
reVX/config/turbine_flicker.py
reVX/config/wind_dirs.py
reVX/handlers/__init__.py
reVX/handlers/database.py
reVX/handlers/geopackage.py
reVX/handlers/geotiff.py
reVX/handlers/layered_h5.py
reVX/handlers/outputs.py
reVX/handlers/sc_points.py
reVX/hybrid_stats/__init__.py
reVX/hybrid_stats/hybrid_stats.py
reVX/hybrid_stats/temporal_agg.py
reVX/least_cost_xmission/README.md
reVX/least_cost_xmission/__init__.py
reVX/least_cost_xmission/least_cost_paths.py
reVX/least_cost_xmission/least_cost_paths_cli.py
reVX/least_cost_xmission/least_cost_xmission.py
reVX/least_cost_xmission/least_cost_xmission_cli.py
reVX/least_cost_xmission/trans_cap_costs.py
reVX/least_cost_xmission/transmission_layer_creator_cli.py
reVX/least_cost_xmission/config/README.md
reVX/least_cost_xmission/config/__init__.py
reVX/least_cost_xmission/config/base_line_costs.json
reVX/least_cost_xmission/config/constants.py
reVX/least_cost_xmission/config/iso_lookup.json
reVX/least_cost_xmission/config/iso_multipliers.json
reVX/least_cost_xmission/config/land_use_classes.json
reVX/least_cost_xmission/config/new_substation_costs.json
reVX/least_cost_xmission/config/power_classes.json
reVX/least_cost_xmission/config/power_to_voltage.json
reVX/least_cost_xmission/config/transformer_costs.json
reVX/least_cost_xmission/config/upgrade_substation_costs.json
reVX/least_cost_xmission/config/xmission_config.py
reVX/least_cost_xmission/layers/__init__.py
reVX/least_cost_xmission/layers/base.py
reVX/least_cost_xmission/layers/dry_cost_creator.py
reVX/least_cost_xmission/layers/layer_creator.py
reVX/least_cost_xmission/layers/masks.py
reVX/least_cost_xmission/layers/utils.py
reVX/offshore/__init__.py
reVX/offshore/assembly_areas.py
reVX/offshore/assembly_areas_cli.py
reVX/offshore/dist_to_ports.py
nrel_revx-0.5.4.dist-info/METADATA
nrel_revx-0.5.4.dist-info/WHEEL
nrel_revx-0.5.4.dist-info/entry_points.txt
nrel_revx-0.5.4.dist-info/top_level.txt
nrel_revx-0.5.4.dist-info/RECORD
