Metadata-Version: 2.4
Name: NREL-reVX
Version: 0.5.4
Summary: National Laboratory of the Rockies' (NLR's) reV eXchange Tool: reVX
Author-email: Michael Rossol <michael.rossol@nrel.gov>
Maintainer-email: Grant Buster <gbuster@nrel.gov>, Paul Pinchuk <ppinchuk@nrel.gov>
License-Expression: BSD-3-Clause
Project-URL: homepage, https://www2.nrel.gov/gis/renewable-energy-potential
Project-URL: documentation, https://nrel.github.io/reVX/
Project-URL: repository, https://github.com/NREL/reVX
Keywords: reVX,NLR
Classifier: Development Status :: 4 - Beta
Classifier: Intended Audience :: Science/Research
Classifier: Natural Language :: English
Classifier: Programming Language :: Python :: 3.9
Classifier: Programming Language :: Python :: 3.10
Classifier: Programming Language :: Python :: 3.11
Classifier: Programming Language :: Python :: 3.12
Classifier: Programming Language :: Python :: 3.13
Requires-Python: >=3.9
License-File: LICENSE
Requires-Dist: addfips<0.5,>=0.4.2
Requires-Dist: fiona<2,>=1.10.1
Requires-Dist: geopandas<2,>=1.0.1
Requires-Dist: NREL-gaps>=0.8.4
Requires-Dist: NREL-reV>=0.14.1
Requires-Dist: NREL-rex>=0.3.3
Requires-Dist: numpy<3,>=2.0.2
Requires-Dist: pandas<3,>=2.2.3
Requires-Dist: psycopg2-binary<3,>=2.9.9
Requires-Dist: pydantic<3,>=2.11.3
Requires-Dist: pyogrio<0.11,>=0.10.0
Requires-Dist: pyproj<4,>=3.6.1
Requires-Dist: pywavelets<2,>=1.6.0
Requires-Dist: rasterio<2,>=1.4.3
Requires-Dist: scikit-image<0.26,>=0.24.0
Requires-Dist: scikit-learn<2,>=1.6.1
Requires-Dist: shapely<3,>=2.0.7
Requires-Dist: toolz<2,>=1.0.0
Provides-Extra: test
Requires-Dist: pytest<9,>=8.4.0; extra == "test"
Provides-Extra: dev
Requires-Dist: flake8; extra == "dev"
Requires-Dist: pre-commit; extra == "dev"
Requires-Dist: pylint; extra == "dev"
Provides-Extra: build
Requires-Dist: build<2,>=1.2.2; extra == "build"
Requires-Dist: pkginfo<2,>=1.10.0; extra == "build"
Requires-Dist: twine<7,>=6.1.0; extra == "build"
Provides-Extra: flicker
Requires-Dist: HOPP<3.3,>=3.2.0; extra == "flicker"
Dynamic: license-file
